norta/__init__.py
norta-0.3.0.dist-info/METADATA
norta-0.3.0.dist-info/WHEEL
norta-0.3.0.dist-info/top_level.txt
norta-0.3.0.dist-info/RECORD
